PyByteBuffer/__init__.py
PyByteBuffer/utils.py
PyByteBuffer-1.0.5.dist-info/LICENSE.md
PyByteBuffer-1.0.5.dist-info/METADATA
PyByteBuffer-1.0.5.dist-info/WHEEL
PyByteBuffer-1.0.5.dist-info/top_level.txt
PyByteBuffer-1.0.5.dist-info/RECORD
